MANIFEST.in
README.rst
setup.cfg
setup.py
csiquant/__init__.py
csiquant/ctypes.pxd
csiquant/dimensions.cpp
csiquant/dimensions.pxd
csiquant/dimensions.pyx
csiquant/quantities.cpp
csiquant/quantities.pxd
csiquant/quantities.pyx
csiquant/si.py
csiquant/util.pyx
csiquant.egg-info/PKG-INFO
csiquant.egg-info/SOURCES.txt
csiquant.egg-info/dependency_links.txt
csiquant.egg-info/not-zip-safe
csiquant.egg-info/requires.txt
csiquant.egg-info/top_level.txt