Metadata-Version: 2.1
Name: csiquant
Version: 1.0.0a1
Summary: cython dimensional analysis and unit tracking utility
Home-page: UNKNOWN
Author: Greg Echelberger
Author-email: gechelberger@gmail.com
License: UNKNOWN
Keywords: c-extension,SI,units,quantities,dimensional analysis
Platform: UNKNOWN
Classifier: Programming Language :: Python
Classifier: License :: OSI Approved :: MIT License
Classifier: Topic :: Scientific/Engineering
Classifier: Operating System :: OS Independent
Classifier: Intended Audience :: Developers
Classifier: Intended Audience :: Science/Research
Provides-Extra: tests
Provides-Extra: dev
